adls2_mcp_server/__init__.py
adls2_mcp_server/client.py
adls2_mcp_server/server.py
adls2_mcp_server/tools/__init__.py
adls2_mcp_server/tools/directories.py
adls2_mcp_server/tools/files.py
adls2_mcp_server/tools/filesystems.py
adls2_mcp_server-0.1.4.dist-info/METADATA
adls2_mcp_server-0.1.4.dist-info/WHEEL
adls2_mcp_server-0.1.4.dist-info/entry_points.txt
adls2_mcp_server-0.1.4.dist-info/licenses/LICENSE
adls2_mcp_server-0.1.4.dist-info/RECORD
