Metadata-Version: 2.4
Name: adls2-mcp-server
Version: 0.1.4
Summary: Azure Data Lake Storage Gen2 Model Context Protocol (MCP) service
Project-URL: Homepage, https://github.com/erikhoward/adls-mcp-server
Project-URL: Bug Tracker, https://github.com/erikhoward/adls-mcp-server/issues
Project-URL: Documentation, https://github.com/erikhoward/adls-mcp-server/tree/main#adls2-mcp-server-
Author-email: Erik Howard <erikhoward@pm.me>
License: MIT
License-File: LICENSE
Keywords: adls,azure,llm,mcp,model-context-protocol
Classifier: Development Status :: 4 - Beta
Classifier: Intended Audience :: Developers
Classifier: License :: OSI Approved :: MIT License
Classifier: Operating System :: OS Independent
Classifier: Programming Language :: Python :: 3
Classifier: Programming Language :: Python :: 3.13
Requires-Python: >=3.13
Requires-Dist: azure-identity>=1.21.0
Requires-Dist: azure-storage-file-datalake>=12.20.0
Requires-Dist: mcp>=1.6.0
Requires-Dist: python-dotenv>=1.1.0
